cdl2r/__init__.py
cdl2r/constants.py
cdl2r/dataset.py
cdl2r/types.py
cdl2r/cythonized/equations.cpython-36m-darwin.so
cdl2r/models/__init__.py
cdl2r/models/components.py
cdl2r/models/differentiation.py
cdl2r/models/implementation.py
tests/__init__.py
tests/test_dataset.py
tests/cythonized/__init__.py
tests/cythonized/test_equations.py
tests/models/__init__.py
tests/models/test_components.py
tests/models/test_differentiation.py
cdl2r-0.1.2.dist-info/LICENSE
cdl2r-0.1.2.dist-info/METADATA
cdl2r-0.1.2.dist-info/WHEEL
cdl2r-0.1.2.dist-info/top_level.txt
cdl2r-0.1.2.dist-info/RECORD
