Metadata-Version: 2.1
Name: cdl2r
Version: 0.1.2
Summary: Combination Dependent Learning to Rank
Home-page: https://github.com/moriaki3193/cdl2r
Author: Moriaki Saigusa
Author-email: moriaki3193@gmail.com
License: Type license() to see the full license text
Keywords: cdl2r L2R LETOR
Platform: UNKNOWN
Classifier: License :: OSI Approved :: MIT License
Classifier: Programming Language :: Python :: 3.7
Requires-Dist: numpy
Requires-Dist: pandas
